{
  "marketing_stripe": {
    "text": "\"FRETE FIXO DE 25,00 PARA BOCAIÚVA E REGIÃO\"",
    "link": "",
    "background": "#ff0000",
    "color": "#ffffff"
  },
  "contacts_stripe": {
    "pages": [
      {}
    ],
    "phone_wpp": true,
    "socials": true
  },
  "categories_list": {
    "featured": [
      "/encordoamentos?Encordoamentos",
      "/instrumentos?Instrumentos",
      "/audio?Áudio",
      "/suportes?Acessórios",
      "/capasbags?Capas/Bags"
    ],
    "random": 0,
    "full_width": true
  },
  "desktop_megamenu": true,
  "search_input": true,
  "alphabetical_order_submenu": true,
  "full_width_submenu": true
}